mclustpy/__init__.py
mclustpy/model.py
mclustpy-0.0.3.dist-info/licenses/LICENSE
mclustpy-0.0.3.dist-info/METADATA
mclustpy-0.0.3.dist-info/WHEEL
mclustpy-0.0.3.dist-info/top_level.txt
mclustpy-0.0.3.dist-info/RECORD
