Metadata-Version: 2.4
Name: mclustpy
Version: 0.0.3
Summary: Clustering using the mclust algorithm.
Home-page: https://github.com/KalinNonchev/mclustpy
Author: KalinNonchev
Author-email: boo@foo.com
License: MIT License
Requires-Python: >=3.8
License-File: LICENSE
Requires-Dist: mclustpy
Dynamic: author
Dynamic: author-email
Dynamic: description
Dynamic: description-content-type
Dynamic: home-page
Dynamic: license
Dynamic: license-file
Dynamic: requires-dist
Dynamic: requires-python
Dynamic: summary
